qalgebra/__init__.py
qalgebra/_flat_api_tools.py
qalgebra/_rules.py
qalgebra/pattern_matching.py
qalgebra/convert/__init__.py
qalgebra/convert/to_qutip.py
qalgebra/convert/to_sympy_matrix.py
qalgebra/core/__init__.py
qalgebra/core/abstract_algebra.py
qalgebra/core/abstract_quantum_algebra.py
qalgebra/core/algebraic_properties.py
qalgebra/core/exceptions.py
qalgebra/core/hilbert_space_algebra.py
qalgebra/core/indexed_operations.py
qalgebra/core/matrix_algebra.py
qalgebra/core/operator_algebra.py
qalgebra/core/scalar_algebra.py
qalgebra/core/state_algebra.py
qalgebra/core/super_operator_algebra.py
qalgebra/library/__init__.py
qalgebra/library/fock_operators.py
qalgebra/library/pauli_matrices.py
qalgebra/library/spin_algebra.py
qalgebra/printing/__init__.py
qalgebra/printing/_precedence.py
qalgebra/printing/_render_head_repr.py
qalgebra/printing/_unicode_mappings.py
qalgebra/printing/asciiprinter.py
qalgebra/printing/base.py
qalgebra/printing/dot.py
qalgebra/printing/latexprinter.py
qalgebra/printing/sreprprinter.py
qalgebra/printing/sympy.py
qalgebra/printing/treeprinting.py
qalgebra/printing/unicodeprinter.py
qalgebra/toolbox/__init__.py
qalgebra/toolbox/commutator_manipulation.py
qalgebra/toolbox/core.py
qalgebra/utils/__init__.py
qalgebra/utils/_attrs.py
qalgebra/utils/check_rules.py
qalgebra/utils/containers.py
qalgebra/utils/indices.py
qalgebra/utils/ordering.py
qalgebra/utils/properties_for_args.py
qalgebra/utils/singleton.py
qalgebra/utils/testing.py
qalgebra/utils/unicode.py
qalgebra-0.2.0.dist-info/LICENSE
qalgebra-0.2.0.dist-info/METADATA
qalgebra-0.2.0.dist-info/WHEEL
qalgebra-0.2.0.dist-info/top_level.txt
qalgebra-0.2.0.dist-info/RECORD
